rtl/convolution/pe.v
module PE (
    input clk,
    input reset,
    input [7:0] in1,
    input [7:0] in2,
    output reg [7:0] out1,
    output reg [7:0] out2,
    output reg [31:0] mac_out
);

    always @(posedge clk or posedge reset) begin
        
        if(reset) begin 
            mac_out <= 0;
            out1 <= 0;
            out2 <= 0;
        end
        else begin
            mac_out <= mac_out + (in1*in2);
            out1 <= in1;
            out2 <= in2;
    end

    end
    
endmodule

rtl/systolic_array.v
`include "pe.v"

module systolic_array (
    input clk,
    input reset,
    input [31:0] a,
    input [31:0] b,
    output [511:0] result
);

wire [7:0] a_in01, a_in02, a_in03, a_out1; 
wire [7:0] a_in11, a_in12, a_in13, a_out2; 
wire [7:0] a_in21, a_in22, a_in23, a_out3; 
wire [7:0] a_in31, a_in32, a_in33, a_out4;

wire [7:0] b_in10, b_in20, b_in30, b_out1;
wire [7:0] b_in11, b_in21, b_in31, b_out2;
wire [7:0] b_in12, b_in22, b_in32, b_out3;
wire [7:0] b_in13, b_in23, b_in33, b_out4;

wire [31:0] result_00, result_01, result_02, result_03;
wire [31:0] result_10, result_11, result_12, result_13;
wire [31:0] result_20, result_21, result_22, result_23;
wire [31:0] result_30, result_31, result_32, result_33;

PE pe_00 (clk, reset, a[7:0], b[7:0], a_in01, b_in10, result_00);
PE pe_01 (clk, reset, a_in01, b[15:8], a_in02, b_in11, result_01);
PE pe_02 (clk, reset, a_in02, b[23:16], a_in03, b_in12, result_02);
PE pe_03 (clk, reset, a_in03, b[31:24], a_out1, b_in13, result_03);

PE pe_10 (clk, reset, a[15:8], b_in10, a_in11, b_in20, result_10);
PE pe_11 (clk, reset, a_in11, b_in11, a_in12, b_in21, result_11);
PE pe_12 (clk, reset, a_in12, b_in12, a_in13, b_in22, result_12);
PE pe_13 (clk, reset, a_in13, b_in13, a_out2, b_in23, result_13);

PE pe_20 (clk, reset, a[23:16], b_in20, a_in21, b_in30, result_20);
PE pe_21 (clk, reset, a_in21, b_in21, a_in22, b_in31, result_21);
PE pe_22 (clk, reset, a_in22, b_in22, a_in23, b_in32, result_22);
PE pe_23 (clk, reset, a_in23, b_in23, a_out3, b_in33, result_23);

PE pe_30 (clk, reset, a[31:24], b_in30, a_in31, b_out1, result_30);
PE pe_31 (clk, reset, a_in31, b_in31, a_in32, b_out2, result_31);
PE pe_32 (clk, reset, a_in32, b_in32, a_in33, b_out3, result_32);
PE pe_33 (clk, reset, a_in33, b_in33, a_out4, b_out4, result_33);

assign result = { result_00, result_01, result_02, result_03,
                  result_10, result_11, result_12, result_13,
                  result_20, result_21, result_22, result_23,
                  result_30, result_31, result_32, result_33 };

endmodule

tb/systolic_array_matmul4x4_tb.v
`timescale 1ns/1ps

module matmul_tb;

    reg clk, reset;
    reg [31:0] a, b;
    wire [511:0] result;

    systolic_array uut(
        .clk(clk),
        .reset(reset),
        .a(a),
        .b(b),
        .result(result)
    );

    initial begin
        clk = 0;
        forever #5 clk = ~clk;
    end

    initial begin
        $dumpfile("matmul4x4_wave.vcd");
        $dumpvars(0, matmul_tb);
        
    end

    initial begin
        
        reset = 1;

        a = 32'h0;
        b = 32'h0;

        #10 reset = 0;

        @(posedge clk);

        a = 32'h00000001;
        b = 32'h00000001;

        @(posedge clk);

        a = 32'h00000502;
        b = 32'h00000502;

        @(posedge clk);

        a = 32'h00090603;
        b = 32'h00090603;

        @(posedge clk);

        a = 32'h0D0A0704;
        b = 32'h0D0A0704;

        @(posedge clk);

        a = 32'h0E0B0800;
        b = 32'h0E0B0800;

        @(posedge clk);

        a = 32'h0F0C0000;
        b = 32'h0F0C0000;

        @(posedge clk);

        a = 32'h01000000;
        b = 32'h01000000;

        @(posedge clk);

        a = 32'h0;
        b = 32'h0;

        repeat(10) @(posedge clk);

        // A:             B:
        // 1 2 3 4        1 5 9 13
        // 5 6 7 8        2 6 10 14
        // 9 10 11 12     3 7 11 15
        // 13 14 15 1     4 8 12 1

        // Result :
        // 30 70 110 90
        // 70 174 278 262
        // 110 278 446 434
        // 90 262 434 591

        $display("========================");
        $display("Result : ");
        $display("%0d %0d %0d %0d", result[511:480], result[479:448], result[447:416], result[415:384]);
        $display("%0d %0d %0d %0d", result[383:352], result[351:320], result[319:288], result[287:256]);
        $display("%0d %0d %0d %0d", result[255:224], result[223:192], result[191:160], result[159:128]);
        $display("%0d %0d %0d %0d", result[127:96], result[95:64], result[63:32], result[31:0]);
         $display("========================");

        #10

        $finish;

    end


endmodule

sim/matmul4x4_wave.vcd
$date
	Fri Dec 26 00:18:55 2025
$end
$version
	Icarus Verilog
$end
$timescale
	1ps
$end
$scope module matmul_tb $end
$var wire 512 ! result [511:0] $end
$var reg 32 " a [31:0] $end
$var reg 32 # b [31:0] $end
$var reg 1 $ clk $end
$var reg 1 % reset $end
$scope module uut $end
$var wire 32 & a [31:0] $end
$var wire 32 ' b [31:0] $end
$var wire 1 $ clk $end
$var wire 1 % reset $end
$var wire 32 ( result_33 [31:0] $end
$var wire 32 ) result_32 [31:0] $end
$var wire 32 * result_31 [31:0] $end
$var wire 32 + result_30 [31:0] $end
$var wire 32 , result_23 [31:0] $end
$var wire 32 - result_22 [31:0] $end
$var wire 32 . result_21 [31:0] $end
$var wire 32 / result_20 [31:0] $end
$var wire 32 0 result_13 [31:0] $end
$var wire 32 1 result_12 [31:0] $end
$var wire 32 2 result_11 [31:0] $end
$var wire 32 3 result_10 [31:0] $end
$var wire 32 4 result_03 [31:0] $end
$var wire 32 5 result_02 [31:0] $end
$var wire 32 6 result_01 [31:0] $end
$var wire 32 7 result_00 [31:0] $end
$var wire 512 8 result [511:0] $end
$var wire 8 9 b_out4 [7:0] $end
$var wire 8 : b_out3 [7:0] $end
$var wire 8 ; b_out2 [7:0] $end
$var wire 8 < b_out1 [7:0] $end
$var wire 8 = b_in33 [7:0] $end
$var wire 8 > b_in32 [7:0] $end
$var wire 8 ? b_in31 [7:0] $end
$var wire 8 @ b_in30 [7:0] $end
$var wire 8 A b_in23 [7:0] $end
$var wire 8 B b_in22 [7:0] $end
$var wire 8 C b_in21 [7:0] $end
$var wire 8 D b_in20 [7:0] $end
$var wire 8 E b_in13 [7:0] $end
$var wire 8 F b_in12 [7:0] $end
$var wire 8 G b_in11 [7:0] $end
$var wire 8 H b_in10 [7:0] $end
$var wire 8 I a_out4 [7:0] $end
$var wire 8 J a_out3 [7:0] $end
$var wire 8 K a_out2 [7:0] $end
$var wire 8 L a_out1 [7:0] $end
$var wire 8 M a_in33 [7:0] $end
$var wire 8 N a_in32 [7:0] $end
$var wire 8 O a_in31 [7:0] $end
$var wire 8 P a_in23 [7:0] $end
$var wire 8 Q a_in22 [7:0] $end
$var wire 8 R a_in21 [7:0] $end
$var wire 8 S a_in13 [7:0] $end
$var wire 8 T a_in12 [7:0] $end
$var wire 8 U a_in11 [7:0] $end
$var wire 8 V a_in03 [7:0] $end
$var wire 8 W a_in02 [7:0] $end
$var wire 8 X a_in01 [7:0] $end
$scope module pe_00 $end
$var wire 1 $ clk $end
$var wire 8 Y in1 [7:0] $end
$var wire 8 Z in2 [7:0] $end
$var wire 1 % reset $end
$var reg 32 [ mac_out [31:0] $end
$var reg 8 \ out1 [7:0] $end
$var reg 8 ] out2 [7:0] $end
$upscope $end
$scope module pe_01 $end
$var wire 1 $ clk $end
$var wire 8 ^ in1 [7:0] $end
$var wire 8 _ in2 [7:0] $end
$var wire 1 % reset $end
$var reg 32 ` mac_out [31:0] $end
$var reg 8 a out1 [7:0] $end
$var reg 8 b out2 [7:0] $end
$upscope $end
$scope module pe_02 $end
$var wire 1 $ clk $end
$var wire 8 c in1 [7:0] $end
$var wire 8 d in2 [7:0] $end
$var wire 1 % reset $end
$var reg 32 e mac_out [31:0] $end
$var reg 8 f out1 [7:0] $end
$var reg 8 g out2 [7:0] $end
$upscope $end
$scope module pe_03 $end
$var wire 1 $ clk $end
$var wire 8 h in1 [7:0] $end
$var wire 8 i in2 [7:0] $end
$var wire 1 % reset $end
$var reg 32 j mac_out [31:0] $end
$var reg 8 k out1 [7:0] $end
$var reg 8 l out2 [7:0] $end
$upscope $end
$scope module pe_10 $end
$var wire 1 $ clk $end
$var wire 8 m in1 [7:0] $end
$var wire 8 n in2 [7:0] $end
$var wire 1 % reset $end
$var reg 32 o mac_out [31:0] $end
$var reg 8 p out1 [7:0] $end
$var reg 8 q out2 [7:0] $end
$upscope $end
$scope module pe_11 $end
$var wire 1 $ clk $end
$var wire 8 r in1 [7:0] $end
$var wire 8 s in2 [7:0] $end
$var wire 1 % reset $end
$var reg 32 t mac_out [31:0] $end
$var reg 8 u out1 [7:0] $end
$var reg 8 v out2 [7:0] $end
$upscope $end
$scope module pe_12 $end
$var wire 1 $ clk $end
$var wire 8 w in1 [7:0] $end
$var wire 8 x in2 [7:0] $end
$var wire 1 % reset $end
$var reg 32 y mac_out [31:0] $end
$var reg 8 z out1 [7:0] $end
$var reg 8 { out2 [7:0] $end
$upscope $end
$scope module pe_13 $end
$var wire 1 $ clk $end
$var wire 8 | in1 [7:0] $end
$var wire 8 } in2 [7:0] $end
$var wire 1 % reset $end
$var reg 32 ~ mac_out [31:0] $end
$var reg 8 !" out1 [7:0] $end
$var reg 8 "" out2 [7:0] $end
$upscope $end
$scope module pe_20 $end
$var wire 1 $ clk $end
$var wire 8 #" in1 [7:0] $end
$var wire 8 $" in2 [7:0] $end
$var wire 1 % reset $end
$var reg 32 %" mac_out [31:0] $end
$var reg 8 &" out1 [7:0] $end
$var reg 8 '" out2 [7:0] $end
$upscope $end
$scope module pe_21 $end
$var wire 1 $ clk $end
$var wire 8 (" in1 [7:0] $end
$var wire 8 )" in2 [7:0] $end
$var wire 1 % reset $end
$var reg 32 *" mac_out [31:0] $end
$var reg 8 +" out1 [7:0] $end
$var reg 8 ," out2 [7:0] $end
$upscope $end
$scope module pe_22 $end
$var wire 1 $ clk $end
$var wire 8 -" in1 [7:0] $end
$var wire 8 ." in2 [7:0] $end
$var wire 1 % reset $end
$var reg 32 /" mac_out [31:0] $end
$var reg 8 0" out1 [7:0] $end
$var reg 8 1" out2 [7:0] $end
$upscope $end
$scope module pe_23 $end
$var wire 1 $ clk $end
$var wire 8 2" in1 [7:0] $end
$var wire 8 3" in2 [7:0] $end
$var wire 1 % reset $end
$var reg 32 4" mac_out [31:0] $end
$var reg 8 5" out1 [7:0] $end
$var reg 8 6" out2 [7:0] $end
$upscope $end
$scope module pe_30 $end
$var wire 1 $ clk $end
$var wire 8 7" in1 [7:0] $end
$var wire 8 8" in2 [7:0] $end
$var wire 1 % reset $end
$var reg 32 9" mac_out [31:0] $end
$var reg 8 :" out1 [7:0] $end
$var reg 8 ;" out2 [7:0] $end
$upscope $end
$scope module pe_31 $end
$var wire 1 $ clk $end
$var wire 8 <" in1 [7:0] $end
$var wire 8 =" in2 [7:0] $end
$var wire 1 % reset $end
$var reg 32 >" mac_out [31:0] $end
$var reg 8 ?" out1 [7:0] $end
$var reg 8 @" out2 [7:0] $end
$upscope $end
$scope module pe_32 $end
$var wire 1 $ clk $end
$var wire 8 A" in1 [7:0] $end
$var wire 8 B" in2 [7:0] $end
$var wire 1 % reset $end
$var reg 32 C" mac_out [31:0] $end
$var reg 8 D" out1 [7:0] $end
$var reg 8 E" out2 [7:0] $end
$upscope $end
$scope module pe_33 $end
$var wire 1 $ clk $end
$var wire 8 F" in1 [7:0] $end
$var wire 8 G" in2 [7:0] $end
$var wire 1 % reset $end
$var reg 32 H" mac_out [31:0] $end
$var reg 8 I" out1 [7:0] $end
$var reg 8 J" out2 [7:0] $end
$upscope $end
$upscope $end
$upscope $end
$enddefinitions $end
#0
$dumpvars
b0 J"
b0 I"
b0 H"
b0 G"
b0 F"
b0 E"
b0 D"
b0 C"
b0 B"
b0 A"
b0 @"
b0 ?"
b0 >"
b0 ="
b0 <"
b0 ;"
b0 :"
b0 9"
b0 8"
b0 7"
b0 6"
b0 5"
b0 4"
b0 3"
b0 2"
b0 1"
b0 0"
b0 /"
b0 ."
b0 -"
b0 ,"
b0 +"
b0 *"
b0 )"
b0 ("
b0 '"
b0 &"
b0 %"
b0 $"
b0 #"
b0 ""
b0 !"
b0 ~
b0 }
b0 |
b0 {
b0 z
b0 y
b0 x
b0 w
b0 v
b0 u
b0 t
b0 s
b0 r
b0 q
b0 p
b0 o
b0 n
b0 m
b0 l
b0 k
b0 j
b0 i
b0 h
b0 g
b0 f
b0 e
b0 d
b0 c
b0 b
b0 a
b0 `
b0 _
b0 ^
b0 ]
b0 \
b0 [
b0 Z
b0 Y
b0 X
b0 W
b0 V
b0 U
b0 T
b0 S
b0 R
b0 Q
b0 P
b0 O
b0 N
b0 M
b0 L
b0 K
b0 J
b0 I
b0 H
b0 G
b0 F
b0 E
b0 D
b0 C
b0 B
b0 A
b0 @
b0 ?
b0 >
b0 =
b0 <
b0 ;
b0 :
b0 9
b0 8
b0 7
b0 6
b0 5
b0 4
b0 3
b0 2
b0 1
b0 0
b0 /
b0 .
b0 -
b0 ,
b0 +
b0 *
b0 )
b0 (
b0 '
b0 &
1%
0$
b0 #
b0 "
b0 !
$end
#5000
1$
#10000
0$
0%
#15000
b1 Z
b1 Y
b1 #
b1 '
b1 "
b1 &
1$
#20000
0$
#25000
b1 H
b1 ]
b1 n
b1 X
b1 \
b1 ^
b1000000000000000000000000000000000000000000000000000000000000000000000000000000000000000000000000000000000000000000000000000000000000000000000000000000000000000000000000000000000000000000000000000000000000000000000000000000000000000000000000000000000000000000000000000000000000000000000000000000000000000000000000000000000000000000000000000000000000000000000000000000000000000000000000000000000000000000000000000000000000000000000000000000000000000000000000000000000000000000000000 !
b1000000000000000000000000000000000000000000000000000000000000000000000000000000000000000000000000000000000000000000000000000000000000000000000000000000000000000000000000000000000000000000000000000000000000000000000000000000000000000000000000000000000000000000000000000000000000000000000000000000000000000000000000000000000000000000000000000000000000000000000000000000000000000000000000000000000000000000000000000000000000000000000000000000000000000000000000000000000000000000000000 8
b1 7
b1 [
b10 Z
b101 _
b10 Y
b101 m
b10100000010 #
b10100000010 '
b10100000010 "
b10100000010 &
1$
#30000
0$
#35000
b10 H
b10 ]
b10 n
b10 X
b10 \
b10 ^
b101 7
b101 [
b101 G
b101 b
b101 s
b1 W
b1 a
b1 c
b101 6
b101 `
b1 D
b1 q
b1 $"
b101 U
b101 p
b101 r
b101000000000000000000000000000001010000000000000000000000000000000000000000000000000000000000000000000000000000000000000000000001010000000000000000000000000000000000000000000000000000000000000000000000000000000000000000000000000000000000000000000000000000000000000000000000000000000000000000000000000000000000000000000000000000000000000000000000000000000000000000000000000000000000000000000000000000000000000000000000000000000000000000000000000000000000000000000000000000000000000000 !
b101000000000000000000000000000001010000000000000000000000000000000000000000000000000000000000000000000000000000000000000000000001010000000000000000000000000000000000000000000000000000000000000000000000000000000000000000000000000000000000000000000000000000000000000000000000000000000000000000000000000000000000000000000000000000000000000000000000000000000000000000000000000000000000000000000000000000000000000000000000000000000000000000000000000000000000000000000000000000000000000000 8
b101 3
b101 o
b11 Z
b110 _
b1001 d
b11 Y
b110 m
b1001 #"
b10010000011000000011 #
b10010000011000000011 '
b10010000011000000011 "
b10010000011000000011 &
1$
#40000
0$
#45000
b1 @
b1 '"
b1 8"
b1001 R
b1001 &"
b1001 ("
b1001 /
b1001 %"
b101 C
b101 v
b101 )"
b101 T
b101 u
b101 w
b11001 2
b11001 t
b10 D
b10 q
b10 $"
b110 U
b110 p
b110 r
b10001 3
b10001 o
b1001 F
b1001 g
b1001 x
b1 V
b1 f
b1 h
b1001 5
b1001 e
b110 G
b110 b
b110 s
b10 W
b10 a
b10 c
b10001 6
b10001 `
b11 H
b11 ]
b11 n
b11 X
b11 \
b11 ^
b1110000000000000000000000000000100010000000000000000000000000000100100000000000000000000000000000000000000000000000000000000000100010000000000000000000000000001100100000000000000000000000000000000000000000000000000000000000000000000000000000000000000000000100100000000000000000000000000000000000000000000000000000000000000000000000000000000000000000000000000000000000000000000000000000000000000000000000000000000000000000000000000000000000000000000000000000000000000000000000000000000 !
b1110000000000000000000000000000100010000000000000000000000000000100100000000000000000000000000000000000000000000000000000000000100010000000000000000000000000001100100000000000000000000000000000000000000000000000000000000000000000000000000000000000000000000100100000000000000000000000000000000000000000000000000000000000000000000000000000000000000000000000000000000000000000000000000000000000000000000000000000000000000000000000000000000000000000000000000000000000000000000000000000000 8
b1110 7
b1110 [
b100 Z
b111 _
b1010 d
b1101 i
b100 Y
b111 m
b1010 #"
b1101 7"
b1101000010100000011100000100 #
b1101000010100000011100000100 '
b1101000010100000011100000100 "
b1101000010100000011100000100 &
1$
#50000
0$
#55000
b100 H
b100 ]
b100 n
b100 X
b100 \
b100 ^
b11110 7
b11110 [
b111 G
b111 b
b111 s
b11 W
b11 a
b11 c
b100110 6
b100110 `
b1010 F
b1010 g
b1010 x
b10 V
b10 f
b10 h
b11101 5
b11101 e
b1101 E
b1101 l
b1101 }
b1 L
b1 k
b1101 4
b1101 j
b11 D
b11 q
b11 $"
b111 U
b111 p
b111 r
b100110 3
b100110 o
b110 C
b110 v
b110 )"
b110 T
b110 u
b110 w
b111101 2
b111101 t
b1001 B
b1001 {
b1001 ."
b101 S
b101 z
b101 |
b101101 1
b101101 y
b10 @
b10 '"
b10 8"
b1010 R
b1010 &"
b1010 ("
b11101 /
b11101 %"
b101 ?
b101 ,"
b101 ="
b1001 Q
b1001 +"
b1001 -"
b101101 .
b101101 *"
b1 <
b1 ;"
b1101 O
b1101 :"
b1101 <"
b11110000000000000000000000000001001100000000000000000000000000001110100000000000000000000000000001101000000000000000000000000001001100000000000000000000000000011110100000000000000000000000000101101000000000000000000000000000000000000000000000000000000000001110100000000000000000000000000101101000000000000000000000000000000000000000000000000000000000000000000000000000000000000000000001101000000000000000000000000000000000000000000000000000000000000000000000000000000000000000000000000 !
b11110000000000000000000000000001001100000000000000000000000000001110100000000000000000000000000001101000000000000000000000000001001100000000000000000000000000011110100000000000000000000000000101101000000000000000000000000000000000000000000000000000000000001110100000000000000000000000000101101000000000000000000000000000000000000000000000000000000000000000000000000000000000000000000001101000000000000000000000000000000000000000000000000000000000000000000000000000000000000000000000000 8
b1101 +
b1101 9"
b0 Z
b1000 _
b1011 d
b1110 i
b0 Y
b1000 m
b1011 #"
b1110 7"
b1110000010110000100000000000 #
b1110000010110000100000000000 '
b1110000010110000100000000000 "
b1110000010110000100000000000 &
1$
#60000
0$
#65000
b101 ;
b101 @"
b1101 N
b1101 ?"
b1101 A"
b1000001 *
b1000001 >"
b10 <
b10 ;"
b1110 O
b1110 :"
b1110 <"
b101001 +
b101001 9"
b1001 >
b1001 1"
b1001 B"
b1001 P
b1001 0"
b1001 2"
b1010001 -
b1010001 /"
b110 ?
b110 ,"
b110 ="
b1010 Q
b1010 +"
b1010 -"
b1101001 .
b1101001 *"
b11 @
b11 '"
b11 8"
b1011 R
b1011 &"
b1011 ("
b111110 /
b111110 %"
b1101 A
b1101 ""
b1101 3"
b101 K
b101 !"
b1000001 0
b1000001 ~
b1010 B
b1010 {
b1010 ."
b110 S
b110 z
b110 |
b1101001 1
b1101001 y
b111 C
b111 v
b111 )"
b111 T
b111 u
b111 w
b1101110 2
b1101110 t
b100 D
b100 q
b100 $"
b1000 U
b1000 p
b1000 r
b1000110 3
b1000110 o
b1110 E
b1110 l
b1110 }
b10 L
b10 k
b101001 4
b101001 j
b1011 F
b1011 g
b1011 x
b11 V
b11 f
b11 h
b111110 5
b111110 e
b1000 G
b1000 b
b1000 s
b100 W
b100 a
b100 c
b11110000000000000000000000000010001100000000000000000000000000011111000000000000000000000000000101001000000000000000000000000010001100000000000000000000000000110111000000000000000000000000001101001000000000000000000000000010000010000000000000000000000000011111000000000000000000000000001101001000000000000000000000000010100010000000000000000000000000000000000000000000000000000000000101001000000000000000000000000010000010000000000000000000000000000000000000000000000000000000000000000 !
b11110000000000000000000000000010001100000000000000000000000000011111000000000000000000000000000101001000000000000000000000000010001100000000000000000000000000110111000000000000000000000000001101001000000000000000000000000010000010000000000000000000000000011111000000000000000000000000001101001000000000000000000000000010100010000000000000000000000000000000000000000000000000000000000101001000000000000000000000000010000010000000000000000000000000000000000000000000000000000000000000000 8
b1000110 6
b1000110 `
b0 H
b0 ]
b0 n
b0 X
b0 \
b0 ^
b0 _
b1100 d
b1111 i
b0 m
b1100 #"
b1111 7"
b1111000011000000000000000000 #
b1111000011000000000000000000 '
b1111000011000000000000000000 "
b1111000011000000000000000000 &
1$
#70000
0$
#75000
b0 G
b0 b
b0 s
b0 W
b0 a
b0 c
b1100 F
b1100 g
b1100 x
b100 V
b100 f
b100 h
b1101110 5
b1101110 e
b1111 E
b1111 l
b1111 }
b11 L
b11 k
b1010110 4
b1010110 j
b0 D
b0 q
b0 $"
b0 U
b0 p
b0 r
b1000 C
b1000 v
b1000 )"
b1000 T
b1000 u
b1000 w
b10101110 2
b10101110 t
b1011 B
b1011 {
b1011 ."
b111 S
b111 z
b111 |
b10110110 1
b10110110 y
b1110 A
b1110 ""
b1110 3"
b110 K
b110 !"
b10010101 0
b10010101 ~
b100 @
b100 '"
b100 8"
b1100 R
b1100 &"
b1100 ("
b1101110 /
b1101110 %"
b111 ?
b111 ,"
b111 ="
b1011 Q
b1011 +"
b1011 -"
b10110110 .
b10110110 *"
b1010 >
b1010 1"
b1010 B"
b1010 P
b1010 0"
b1010 2"
b10110101 -
b10110101 /"
b1101 =
b1101 6"
b1101 G"
b1001 J
b1001 5"
b1110101 ,
b1110101 4"
b11 <
b11 ;"
b1111 O
b1111 :"
b1111 <"
b1010110 +
b1010110 9"
b110 ;
b110 @"
b1110 N
b1110 ?"
b1110 A"
b10010101 *
b10010101 >"
b1001 :
b1001 E"
b1101 M
b1101 D"
b1101 F"
b11110000000000000000000000000010001100000000000000000000000000110111000000000000000000000000001010110000000000000000000000000010001100000000000000000000000001010111000000000000000000000000010110110000000000000000000000000100101010000000000000000000000000110111000000000000000000000000010110110000000000000000000000000101101010000000000000000000000000111010100000000000000000000000001010110000000000000000000000000100101010000000000000000000000000111010100000000000000000000000000000000 !
b11110000000000000000000000000010001100000000000000000000000000110111000000000000000000000000001010110000000000000000000000000010001100000000000000000000000001010111000000000000000000000000010110110000000000000000000000000100101010000000000000000000000000110111000000000000000000000000010110110000000000000000000000000101101010000000000000000000000000111010100000000000000000000000001010110000000000000000000000000100101010000000000000000000000000111010100000000000000000000000000000000 8
b1110101 )
b1110101 C"
b0 d
b1 i
b0 #"
b1 7"
b1000000000000000000000000 #
b1000000000000000000000000 '
b1000000000000000000000000 "
b1000000000000000000000000 &
1$
#80000
0$
#85000
b1101 9
b1101 J"
b1101 I
b1101 I"
b10101001 (
b10101001 H"
b1010 :
b1010 E"
b1110 M
b1110 D"
b1110 F"
b100000001 )
b100000001 C"
b111 ;
b111 @"
b1111 N
b1111 ?"
b1111 A"
b11111110 *
b11111110 >"
b100 <
b100 ;"
b1 O
b1 :"
b1 <"
b1011010 +
b1011010 9"
b1110 =
b1110 6"
b1110 G"
b1010 J
b1010 5"
b100000001 ,
b100000001 4"
b1011 >
b1011 1"
b1011 B"
b1011 P
b1011 0"
b1011 2"
b100101110 -
b100101110 /"
b1000 ?
b1000 ,"
b1000 ="
b1100 Q
b1100 +"
b1100 -"
b100010110 .
b100010110 *"
b0 @
b0 '"
b0 8"
b0 R
b0 &"
b0 ("
b1111 A
b1111 ""
b1111 3"
b111 K
b111 !"
b11111110 0
b11111110 ~
b1100 B
b1100 {
b1100 ."
b1000 S
b1000 z
b1000 |
b100010110 1
b100010110 y
b0 C
b0 v
b0 )"
b0 T
b0 u
b0 w
b1 E
b1 l
b1 }
b100 L
b100 k
b11110000000000000000000000000010001100000000000000000000000000110111000000000000000000000000001011010000000000000000000000000010001100000000000000000000000001010111000000000000000000000000100010110000000000000000000000000111111100000000000000000000000000110111000000000000000000000000100010110000000000000000000000001001011100000000000000000000000010000000100000000000000000000000001011010000000000000000000000000111111100000000000000000000000010000000100000000000000000000000010101001 !
b11110000000000000000000000000010001100000000000000000000000000110111000000000000000000000000001011010000000000000000000000000010001100000000000000000000000001010111000000000000000000000000100010110000000000000000000000000111111100000000000000000000000000110111000000000000000000000000100010110000000000000000000000001001011100000000000000000000000010000000100000000000000000000000001011010000000000000000000000000111111100000000000000000000000010000000100000000000000000000000010101001 8
b1011010 4
b1011010 j
b0 F
b0 g
b0 x
b0 V
b0 f
b0 h
b0 i
b0 7"
b0 #
b0 '
b0 "
b0 &
1$
#90000
0$
#95000
b0 E
b0 l
b0 }
b0 L
b0 k
b0 B
b0 {
b0 ."
b0 S
b0 z
b0 |
b1 A
b1 ""
b1 3"
b1000 K
b1000 !"
b100000110 0
b100000110 ~
b0 ?
b0 ,"
b0 ="
b0 Q
b0 +"
b0 -"
b1100 >
b1100 1"
b1100 B"
b1100 P
b1100 0"
b1100 2"
b110111110 -
b110111110 /"
b1111 =
b1111 6"
b1111 G"
b1011 J
b1011 5"
b110100110 ,
b110100110 4"
b0 <
b0 ;"
b0 O
b0 :"
b0 <"
b1000 ;
b1000 @"
b1 N
b1 ?"
b1 A"
b100000110 *
b100000110 >"
b1011 :
b1011 E"
b1111 M
b1111 D"
b1111 F"
b110100110 )
b110100110 C"
b1110 9
b1110 J"
b1110 I
b1110 I"
b11110000000000000000000000000010001100000000000000000000000000110111000000000000000000000000001011010000000000000000000000000010001100000000000000000000000001010111000000000000000000000000100010110000000000000000000000001000001100000000000000000000000000110111000000000000000000000000100010110000000000000000000000001101111100000000000000000000000011010011000000000000000000000000001011010000000000000000000000001000001100000000000000000000000011010011000000000000000000000000101101101 !
b11110000000000000000000000000010001100000000000000000000000000110111000000000000000000000000001011010000000000000000000000000010001100000000000000000000000001010111000000000000000000000000100010110000000000000000000000001000001100000000000000000000000000110111000000000000000000000000100010110000000000000000000000001101111100000000000000000000000011010011000000000000000000000000001011010000000000000000000000001000001100000000000000000000000011010011000000000000000000000000101101101 8
b101101101 (
b101101101 H"
1$
#100000
0$
#105000
b1111 9
b1111 J"
b1111 I
b1111 I"
b1001001110 (
b1001001110 H"
b1100 :
b1100 E"
b1 M
b1 D"
b1 F"
b110110010 )
b110110010 C"
b0 ;
b0 @"
b0 N
b0 ?"
b0 A"
b1 =
b1 6"
b1 G"
b1100 J
b1100 5"
b11110000000000000000000000000010001100000000000000000000000000110111000000000000000000000000001011010000000000000000000000000010001100000000000000000000000001010111000000000000000000000000100010110000000000000000000000001000001100000000000000000000000000110111000000000000000000000000100010110000000000000000000000001101111100000000000000000000000011011001000000000000000000000000001011010000000000000000000000001000001100000000000000000000000011011001000000000000000000000001001001110 !
b11110000000000000000000000000010001100000000000000000000000000110111000000000000000000000000001011010000000000000000000000000010001100000000000000000000000001010111000000000000000000000000100010110000000000000000000000001000001100000000000000000000000000110111000000000000000000000000100010110000000000000000000000001101111100000000000000000000000011011001000000000000000000000000001011010000000000000000000000001000001100000000000000000000000011011001000000000000000000000001001001110 8
b110110010 ,
b110110010 4"
b0 >
b0 1"
b0 B"
b0 P
b0 0"
b0 2"
b0 A
b0 ""
b0 3"
b0 K
b0 !"
1$
#110000
0$
#115000
b0 =
b0 6"
b0 G"
b0 J
b0 5"
b0 :
b0 E"
b0 M
b0 D"
b0 F"
b1 9
b1 J"
b1 I
b1 I"
b11110000000000000000000000000010001100000000000000000000000000110111000000000000000000000000001011010000000000000000000000000010001100000000000000000000000001010111000000000000000000000000100010110000000000000000000000001000001100000000000000000000000000110111000000000000000000000000100010110000000000000000000000001101111100000000000000000000000011011001000000000000000000000000001011010000000000000000000000001000001100000000000000000000000011011001000000000000000000000001001001111 !
b11110000000000000000000000000010001100000000000000000000000000110111000000000000000000000000001011010000000000000000000000000010001100000000000000000000000001010111000000000000000000000000100010110000000000000000000000001000001100000000000000000000000000110111000000000000000000000000100010110000000000000000000000001101111100000000000000000000000011011001000000000000000000000000001011010000000000000000000000001000001100000000000000000000000011011001000000000000000000000001001001111 8
b1001001111 (
b1001001111 H"
1$
#120000
0$
#125000
b0 9
b0 J"
b0 I
b0 I"
1$
