rtl/convolution/pe.v
module PE (
    input clk,
    input reset,
    input [7:0] in1,
    input [7:0] in2,
    output reg [7:0] out1,
    output reg [7:0] out2,
    output reg [31:0] mac_out
);

    always @(posedge clk or posedge reset) begin
        
        if(reset) begin 
            mac_out <= 0;
            out1 <= 0;
            out2 <= 0;
        end
        else begin
            mac_out <= mac_out + (in1*in2);
            out1 <= in1;
            out2 <= in2;
    end

    end
    
endmodule

rtl/systolic_array.v
`include "pe.v"

module systolic_array (
    input clk,
    input reset,
    input [31:0] a,
    input [31:0] b,
    output [511:0] result
);

wire [7:0] a_in01, a_in02, a_in03, a_out1; 
wire [7:0] a_in11, a_in12, a_in13, a_out2; 
wire [7:0] a_in21, a_in22, a_in23, a_out3; 
wire [7:0] a_in31, a_in32, a_in33, a_out4;

wire [7:0] b_in10, b_in20, b_in30, b_out1;
wire [7:0] b_in11, b_in21, b_in31, b_out2;
wire [7:0] b_in12, b_in22, b_in32, b_out3;
wire [7:0] b_in13, b_in23, b_in33, b_out4;

wire [31:0] result_00, result_01, result_02, result_03;
wire [31:0] result_10, result_11, result_12, result_13;
wire [31:0] result_20, result_21, result_22, result_23;
wire [31:0] result_30, result_31, result_32, result_33;

PE pe_00 (clk, reset, a[7:0], b[7:0], a_in01, b_in10, result_00);
PE pe_01 (clk, reset, a_in01, b[15:8], a_in02, b_in11, result_01);
PE pe_02 (clk, reset, a_in02, b[23:16], a_in03, b_in12, result_02);
PE pe_03 (clk, reset, a_in03, b[31:24], a_out1, b_in13, result_03);

PE pe_10 (clk, reset, a[15:8], b_in10, a_in11, b_in20, result_10);
PE pe_11 (clk, reset, a_in11, b_in11, a_in12, b_in21, result_11);
PE pe_12 (clk, reset, a_in12, b_in12, a_in13, b_in22, result_12);
PE pe_13 (clk, reset, a_in13, b_in13, a_out2, b_in23, result_13);

PE pe_20 (clk, reset, a[23:16], b_in20, a_in21, b_in30, result_20);
PE pe_21 (clk, reset, a_in21, b_in21, a_in22, b_in31, result_21);
PE pe_22 (clk, reset, a_in22, b_in22, a_in23, b_in32, result_22);
PE pe_23 (clk, reset, a_in23, b_in23, a_out3, b_in33, result_23);

PE pe_30 (clk, reset, a[31:24], b_in30, a_in31, b_out1, result_30);
PE pe_31 (clk, reset, a_in31, b_in31, a_in32, b_out2, result_31);
PE pe_32 (clk, reset, a_in32, b_in32, a_in33, b_out3, result_32);
PE pe_33 (clk, reset, a_in33, b_in33, a_out4, b_out4, result_33);

assign result = { result_00, result_01, result_02, result_03,
                  result_10, result_11, result_12, result_13,
                  result_20, result_21, result_22, result_23,
                  result_30, result_31, result_32, result_33 };

endmodule

tb/systolic_array_convolution_tb.v
`timescale 1ns/1ps

module convolution_tb;

    reg clk, reset;
    reg [31:0] a, b;
    wire [511:0] result;

    systolic_array uut (
        .clk(clk),
        .reset(reset),
        .a(a),
        .b(b),
        .result(result)
    );

    initial begin
        clk = 0;
        forever #5 clk = ~clk;
    end

    initial begin
        $dumpfile("convolution_wave.vcd");
        $dumpvars(0, convolution_tb);
    end

    initial begin

        reset = 1;

        a = 32'h0;
        b = 32'h0;

        #10 reset = 0;

        @(posedge clk);

        a = 32'h00000001;
        b = 32'h00000001;

        @(posedge clk);

        a = 32'h00000302;
        b = 32'h00000000;

        @(posedge clk);

        a = 32'h00090405;
        b = 32'h00000000;

        @(posedge clk);

        a = 32'h0B0A0706;
        b = 32'h00000001;

        @(posedge clk);

        a = 32'h0C0D0800;
        b = 32'h00000000;

        @(posedge clk);

        a = 32'h0F0E0000;
        b = 32'h00000000;

        @(posedge clk);

        a = 32'h01000000;
        b = 32'h00000000;

        @(posedge clk);

        a = 32'h0;
        b = 32'h0;

        repeat(10) @(posedge clk);

        // A:             B:
        // 1 2 3 4        1 0 
        // 5 6 7 8        0 1
        // 9 10 11 12     
        // 13 14 15 1

        // Im2Col :
        //
        // Stride = 2
        //
        // Input1 :          Input2 :
        // 1 2 5 6           1 0 0 0
        // 3 4 7 8           0 0 0 0
        // 9 10 13 14        0 0 0 0
        // 11 12 15 0        1 0 0 0

        // Result :
        // 7 11
        // 23 12

        repeat(10) @(posedge clk);

        $display("========================");
        $display("Result : ");

        $display("%0d %0d", result[15*32 +: 32], result[11*32 +: 32]);
        $display("%0d %0d", result[7*32 +: 32], result[3*32 +: 32]);

        $display("========================");

        #10

        $finish;

    end

endmodule

sim/convolution/convolution_wave.vcd
$date
	Sun Mar 01 21:19:43 2026
$end
$version
	Icarus Verilog
$end
$timescale
	1ps
$end
$scope module convolution_tb $end
$var wire 512 ! result [511:0] $end
$var reg 32 " a [31:0] $end
$var reg 32 # b [31:0] $end
$var reg 1 $ clk $end
$var reg 1 % reset $end
$scope module uut $end
$var wire 32 & a [31:0] $end
$var wire 32 ' b [31:0] $end
$var wire 1 $ clk $end
$var wire 1 % reset $end
$var wire 32 ( result_33 [31:0] $end
$var wire 32 ) result_32 [31:0] $end
$var wire 32 * result_31 [31:0] $end
$var wire 32 + result_30 [31:0] $end
$var wire 32 , result_23 [31:0] $end
$var wire 32 - result_22 [31:0] $end
$var wire 32 . result_21 [31:0] $end
$var wire 32 / result_20 [31:0] $end
$var wire 32 0 result_13 [31:0] $end
$var wire 32 1 result_12 [31:0] $end
$var wire 32 2 result_11 [31:0] $end
$var wire 32 3 result_10 [31:0] $end
$var wire 32 4 result_03 [31:0] $end
$var wire 32 5 result_02 [31:0] $end
$var wire 32 6 result_01 [31:0] $end
$var wire 32 7 result_00 [31:0] $end
$var wire 512 8 result [511:0] $end
$var wire 8 9 b_out4 [7:0] $end
$var wire 8 : b_out3 [7:0] $end
$var wire 8 ; b_out2 [7:0] $end
$var wire 8 < b_out1 [7:0] $end
$var wire 8 = b_in33 [7:0] $end
$var wire 8 > b_in32 [7:0] $end
$var wire 8 ? b_in31 [7:0] $end
$var wire 8 @ b_in30 [7:0] $end
$var wire 8 A b_in23 [7:0] $end
$var wire 8 B b_in22 [7:0] $end
$var wire 8 C b_in21 [7:0] $end
$var wire 8 D b_in20 [7:0] $end
$var wire 8 E b_in13 [7:0] $end
$var wire 8 F b_in12 [7:0] $end
$var wire 8 G b_in11 [7:0] $end
$var wire 8 H b_in10 [7:0] $end
$var wire 8 I a_out4 [7:0] $end
$var wire 8 J a_out3 [7:0] $end
$var wire 8 K a_out2 [7:0] $end
$var wire 8 L a_out1 [7:0] $end
$var wire 8 M a_in33 [7:0] $end
$var wire 8 N a_in32 [7:0] $end
$var wire 8 O a_in31 [7:0] $end
$var wire 8 P a_in23 [7:0] $end
$var wire 8 Q a_in22 [7:0] $end
$var wire 8 R a_in21 [7:0] $end
$var wire 8 S a_in13 [7:0] $end
$var wire 8 T a_in12 [7:0] $end
$var wire 8 U a_in11 [7:0] $end
$var wire 8 V a_in03 [7:0] $end
$var wire 8 W a_in02 [7:0] $end
$var wire 8 X a_in01 [7:0] $end
$scope module pe_00 $end
$var wire 1 $ clk $end
$var wire 8 Y in1 [7:0] $end
$var wire 8 Z in2 [7:0] $end
$var wire 1 % reset $end
$var reg 32 [ mac_out [31:0] $end
$var reg 8 \ out1 [7:0] $end
$var reg 8 ] out2 [7:0] $end
$upscope $end
$scope module pe_01 $end
$var wire 1 $ clk $end
$var wire 8 ^ in1 [7:0] $end
$var wire 8 _ in2 [7:0] $end
$var wire 1 % reset $end
$var reg 32 ` mac_out [31:0] $end
$var reg 8 a out1 [7:0] $end
$var reg 8 b out2 [7:0] $end
$upscope $end
$scope module pe_02 $end
$var wire 1 $ clk $end
$var wire 8 c in1 [7:0] $end
$var wire 8 d in2 [7:0] $end
$var wire 1 % reset $end
$var reg 32 e mac_out [31:0] $end
$var reg 8 f out1 [7:0] $end
$var reg 8 g out2 [7:0] $end
$upscope $end
$scope module pe_03 $end
$var wire 1 $ clk $end
$var wire 8 h in1 [7:0] $end
$var wire 8 i in2 [7:0] $end
$var wire 1 % reset $end
$var reg 32 j mac_out [31:0] $end
$var reg 8 k out1 [7:0] $end
$var reg 8 l out2 [7:0] $end
$upscope $end
$scope module pe_10 $end
$var wire 1 $ clk $end
$var wire 8 m in1 [7:0] $end
$var wire 8 n in2 [7:0] $end
$var wire 1 % reset $end
$var reg 32 o mac_out [31:0] $end
$var reg 8 p out1 [7:0] $end
$var reg 8 q out2 [7:0] $end
$upscope $end
$scope module pe_11 $end
$var wire 1 $ clk $end
$var wire 8 r in1 [7:0] $end
$var wire 8 s in2 [7:0] $end
$var wire 1 % reset $end
$var reg 32 t mac_out [31:0] $end
$var reg 8 u out1 [7:0] $end
$var reg 8 v out2 [7:0] $end
$upscope $end
$scope module pe_12 $end
$var wire 1 $ clk $end
$var wire 8 w in1 [7:0] $end
$var wire 8 x in2 [7:0] $end
$var wire 1 % reset $end
$var reg 32 y mac_out [31:0] $end
$var reg 8 z out1 [7:0] $end
$var reg 8 { out2 [7:0] $end
$upscope $end
$scope module pe_13 $end
$var wire 1 $ clk $end
$var wire 8 | in1 [7:0] $end
$var wire 8 } in2 [7:0] $end
$var wire 1 % reset $end
$var reg 32 ~ mac_out [31:0] $end
$var reg 8 !" out1 [7:0] $end
$var reg 8 "" out2 [7:0] $end
$upscope $end
$scope module pe_20 $end
$var wire 1 $ clk $end
$var wire 8 #" in1 [7:0] $end
$var wire 8 $" in2 [7:0] $end
$var wire 1 % reset $end
$var reg 32 %" mac_out [31:0] $end
$var reg 8 &" out1 [7:0] $end
$var reg 8 '" out2 [7:0] $end
$upscope $end
$scope module pe_21 $end
$var wire 1 $ clk $end
$var wire 8 (" in1 [7:0] $end
$var wire 8 )" in2 [7:0] $end
$var wire 1 % reset $end
$var reg 32 *" mac_out [31:0] $end
$var reg 8 +" out1 [7:0] $end
$var reg 8 ," out2 [7:0] $end
$upscope $end
$scope module pe_22 $end
$var wire 1 $ clk $end
$var wire 8 -" in1 [7:0] $end
$var wire 8 ." in2 [7:0] $end
$var wire 1 % reset $end
$var reg 32 /" mac_out [31:0] $end
$var reg 8 0" out1 [7:0] $end
$var reg 8 1" out2 [7:0] $end
$upscope $end
$scope module pe_23 $end
$var wire 1 $ clk $end
$var wire 8 2" in1 [7:0] $end
$var wire 8 3" in2 [7:0] $end
$var wire 1 % reset $end
$var reg 32 4" mac_out [31:0] $end
$var reg 8 5" out1 [7:0] $end
$var reg 8 6" out2 [7:0] $end
$upscope $end
$scope module pe_30 $end
$var wire 1 $ clk $end
$var wire 8 7" in1 [7:0] $end
$var wire 8 8" in2 [7:0] $end
$var wire 1 % reset $end
$var reg 32 9" mac_out [31:0] $end
$var reg 8 :" out1 [7:0] $end
$var reg 8 ;" out2 [7:0] $end
$upscope $end
$scope module pe_31 $end
$var wire 1 $ clk $end
$var wire 8 <" in1 [7:0] $end
$var wire 8 =" in2 [7:0] $end
$var wire 1 % reset $end
$var reg 32 >" mac_out [31:0] $end
$var reg 8 ?" out1 [7:0] $end
$var reg 8 @" out2 [7:0] $end
$upscope $end
$scope module pe_32 $end
$var wire 1 $ clk $end
$var wire 8 A" in1 [7:0] $end
$var wire 8 B" in2 [7:0] $end
$var wire 1 % reset $end
$var reg 32 C" mac_out [31:0] $end
$var reg 8 D" out1 [7:0] $end
$var reg 8 E" out2 [7:0] $end
$upscope $end
$scope module pe_33 $end
$var wire 1 $ clk $end
$var wire 8 F" in1 [7:0] $end
$var wire 8 G" in2 [7:0] $end
$var wire 1 % reset $end
$var reg 32 H" mac_out [31:0] $end
$var reg 8 I" out1 [7:0] $end
$var reg 8 J" out2 [7:0] $end
$upscope $end
$upscope $end
$upscope $end
$enddefinitions $end
#0
$dumpvars
b0 J"
b0 I"
b0 H"
b0 G"
b0 F"
b0 E"
b0 D"
b0 C"
b0 B"
b0 A"
b0 @"
b0 ?"
b0 >"
b0 ="
b0 <"
b0 ;"
b0 :"
b0 9"
b0 8"
b0 7"
b0 6"
b0 5"
b0 4"
b0 3"
b0 2"
b0 1"
b0 0"
b0 /"
b0 ."
b0 -"
b0 ,"
b0 +"
b0 *"
b0 )"
b0 ("
b0 '"
b0 &"
b0 %"
b0 $"
b0 #"
b0 ""
b0 !"
b0 ~
b0 }
b0 |
b0 {
b0 z
b0 y
b0 x
b0 w
b0 v
b0 u
b0 t
b0 s
b0 r
b0 q
b0 p
b0 o
b0 n
b0 m
b0 l
b0 k
b0 j
b0 i
b0 h
b0 g
b0 f
b0 e
b0 d
b0 c
b0 b
b0 a
b0 `
b0 _
b0 ^
b0 ]
b0 \
b0 [
b0 Z
b0 Y
b0 X
b0 W
b0 V
b0 U
b0 T
b0 S
b0 R
b0 Q
b0 P
b0 O
b0 N
b0 M
b0 L
b0 K
b0 J
b0 I
b0 H
b0 G
b0 F
b0 E
b0 D
b0 C
b0 B
b0 A
b0 @
b0 ?
b0 >
b0 =
b0 <
b0 ;
b0 :
b0 9
b0 8
b0 7
b0 6
b0 5
b0 4
b0 3
b0 2
b0 1
b0 0
b0 /
b0 .
b0 -
b0 ,
b0 +
b0 *
b0 )
b0 (
b0 '
b0 &
1%
0$
b0 #
b0 "
b0 !
$end
#5000
1$
#10000
0$
0%
#15000
b1 Z
b1 Y
b1 #
b1 '
b1 "
b1 &
1$
#20000
0$
#25000
b1 H
b1 ]
b1 n
b1 X
b1 \
b1 ^
b1000000000000000000000000000000000000000000000000000000000000000000000000000000000000000000000000000000000000000000000000000000000000000000000000000000000000000000000000000000000000000000000000000000000000000000000000000000000000000000000000000000000000000000000000000000000000000000000000000000000000000000000000000000000000000000000000000000000000000000000000000000000000000000000000000000000000000000000000000000000000000000000000000000000000000000000000000000000000000000000000 !
b1000000000000000000000000000000000000000000000000000000000000000000000000000000000000000000000000000000000000000000000000000000000000000000000000000000000000000000000000000000000000000000000000000000000000000000000000000000000000000000000000000000000000000000000000000000000000000000000000000000000000000000000000000000000000000000000000000000000000000000000000000000000000000000000000000000000000000000000000000000000000000000000000000000000000000000000000000000000000000000000000 8
b1 7
b1 [
b0 Z
b10 Y
b11 m
b0 #
b0 '
b1100000010 "
b1100000010 &
1$
#30000
0$
#35000
b0 H
b0 ]
b0 n
b10 X
b10 \
b10 ^
b1 W
b1 a
b1 c
b1 D
b1 q
b1 $"
b11 U
b11 p
b11 r
b1000000000000000000000000000000000000000000000000000000000000000000000000000000000000000000000000000000000000000000000000000000110000000000000000000000000000000000000000000000000000000000000000000000000000000000000000000000000000000000000000000000000000000000000000000000000000000000000000000000000000000000000000000000000000000000000000000000000000000000000000000000000000000000000000000000000000000000000000000000000000000000000000000000000000000000000000000000000000000000000000 !
b1000000000000000000000000000000000000000000000000000000000000000000000000000000000000000000000000000000000000000000000000000000110000000000000000000000000000000000000000000000000000000000000000000000000000000000000000000000000000000000000000000000000000000000000000000000000000000000000000000000000000000000000000000000000000000000000000000000000000000000000000000000000000000000000000000000000000000000000000000000000000000000000000000000000000000000000000000000000000000000000000 8
b11 3
b11 o
b101 Y
b100 m
b1001 #"
b10010000010000000101 "
b10010000010000000101 &
1$
#40000
0$
#45000
b1 @
b1 '"
b1 8"
b1001 R
b1001 &"
b1001 ("
b1000000000000000000000000000000000000000000000000000000000000000000000000000000000000000000000000000000000000000000000000000000110000000000000000000000000000000000000000000000000000000000000000000000000000000000000000000000000000000000000000000000000000100100000000000000000000000000000000000000000000000000000000000000000000000000000000000000000000000000000000000000000000000000000000000000000000000000000000000000000000000000000000000000000000000000000000000000000000000000000000 !
b1000000000000000000000000000000000000000000000000000000000000000000000000000000000000000000000000000000000000000000000000000000110000000000000000000000000000000000000000000000000000000000000000000000000000000000000000000000000000000000000000000000000000100100000000000000000000000000000000000000000000000000000000000000000000000000000000000000000000000000000000000000000000000000000000000000000000000000000000000000000000000000000000000000000000000000000000000000000000000000000000 8
b1001 /
b1001 %"
b11 T
b11 u
b11 w
b0 D
b0 q
b0 $"
b100 U
b100 p
b100 r
b1 V
b1 f
b1 h
b10 W
b10 a
b10 c
b101 X
b101 \
b101 ^
b1 Z
b110 Y
b111 m
b1010 #"
b1011 7"
b1 #
b1 '
b1011000010100000011100000110 "
b1011000010100000011100000110 &
1$
#50000
0$
#55000
b1 H
b1 ]
b1 n
b110 X
b110 \
b110 ^
b111 7
b111 [
b101 W
b101 a
b101 c
b10 V
b10 f
b10 h
b1 L
b1 k
b111 U
b111 p
b111 r
b100 T
b100 u
b100 w
b11 S
b11 z
b11 |
b0 @
b0 '"
b0 8"
b1010 R
b1010 &"
b1010 ("
b1001 Q
b1001 +"
b1001 -"
b1 <
b1 ;"
b1011 O
b1011 :"
b1011 <"
b111000000000000000000000000000000000000000000000000000000000000000000000000000000000000000000000000000000000000000000000000000000110000000000000000000000000000000000000000000000000000000000000000000000000000000000000000000000000000000000000000000000000000100100000000000000000000000000000000000000000000000000000000000000000000000000000000000000000000000000000000000000000000000000001011000000000000000000000000000000000000000000000000000000000000000000000000000000000000000000000000 !
b111000000000000000000000000000000000000000000000000000000000000000000000000000000000000000000000000000000000000000000000000000000110000000000000000000000000000000000000000000000000000000000000000000000000000000000000000000000000000000000000000000000000000100100000000000000000000000000000000000000000000000000000000000000000000000000000000000000000000000000000000000000000000000000001011000000000000000000000000000000000000000000000000000000000000000000000000000000000000000000000000 8
b1011 +
b1011 9"
b0 Z
b0 Y
b1000 m
b1101 #"
b1100 7"
b0 #
b0 '
b1100000011010000100000000000 "
b1100000011010000100000000000 &
1$
#60000
0$
#65000
b1011 N
b1011 ?"
b1011 A"
b0 <
b0 ;"
b1100 O
b1100 :"
b1100 <"
b1001 P
b1001 0"
b1001 2"
b1010 Q
b1010 +"
b1010 -"
b1101 R
b1101 &"
b1101 ("
b11 K
b11 !"
b100 S
b100 z
b100 |
b111 T
b111 u
b111 w
b1 D
b1 q
b1 $"
b1000 U
b1000 p
b1000 r
b111000000000000000000000000000000000000000000000000000000000000000000000000000000000000000000000000000000000000000000000000000010110000000000000000000000000000000000000000000000000000000000000000000000000000000000000000000000000000000000000000000000000000100100000000000000000000000000000000000000000000000000000000000000000000000000000000000000000000000000000000000000000000000000001011000000000000000000000000000000000000000000000000000000000000000000000000000000000000000000000000 !
b111000000000000000000000000000000000000000000000000000000000000000000000000000000000000000000000000000000000000000000000000000010110000000000000000000000000000000000000000000000000000000000000000000000000000000000000000000000000000000000000000000000000000100100000000000000000000000000000000000000000000000000000000000000000000000000000000000000000000000000000000000000000000000000001011000000000000000000000000000000000000000000000000000000000000000000000000000000000000000000000000 8
b1011 3
b1011 o
b10 L
b10 k
b101 V
b101 f
b101 h
b110 W
b110 a
b110 c
b0 H
b0 ]
b0 n
b0 X
b0 \
b0 ^
b0 m
b1110 #"
b1111 7"
b1111000011100000000000000000 "
b1111000011100000000000000000 &
1$
#70000
0$
#75000
b0 W
b0 a
b0 c
b110 V
b110 f
b110 h
b101 L
b101 k
b0 D
b0 q
b0 $"
b0 U
b0 p
b0 r
b1000 T
b1000 u
b1000 w
b111 S
b111 z
b111 |
b100 K
b100 !"
b1 @
b1 '"
b1 8"
b1110 R
b1110 &"
b1110 ("
b111000000000000000000000000000000000000000000000000000000000000000000000000000000000000000000000000000000000000000000000000000010110000000000000000000000000000000000000000000000000000000000000000000000000000000000000000000000000000000000000000000000000001011100000000000000000000000000000000000000000000000000000000000000000000000000000000000000000000000000000000000000000000000000001011000000000000000000000000000000000000000000000000000000000000000000000000000000000000000000000000 !
b111000000000000000000000000000000000000000000000000000000000000000000000000000000000000000000000000000000000000000000000000000010110000000000000000000000000000000000000000000000000000000000000000000000000000000000000000000000000000000000000000000000000001011100000000000000000000000000000000000000000000000000000000000000000000000000000000000000000000000000000000000000000000000000001011000000000000000000000000000000000000000000000000000000000000000000000000000000000000000000000000 8
b10111 /
b10111 %"
b1101 Q
b1101 +"
b1101 -"
b1010 P
b1010 0"
b1010 2"
b1001 J
b1001 5"
b1111 O
b1111 :"
b1111 <"
b1100 N
b1100 ?"
b1100 A"
b1011 M
b1011 D"
b1011 F"
b0 #"
b1 7"
b1000000000000000000000000 "
b1000000000000000000000000 &
1$
#80000
0$
#85000
b1011 I
b1011 I"
b1100 M
b1100 D"
b1100 F"
b1111 N
b1111 ?"
b1111 A"
b1 <
b1 ;"
b1 O
b1 :"
b1 <"
b111000000000000000000000000000000000000000000000000000000000000000000000000000000000000000000000000000000000000000000000000000010110000000000000000000000000000000000000000000000000000000000000000000000000000000000000000000000000000000000000000000000000001011100000000000000000000000000000000000000000000000000000000000000000000000000000000000000000000000000000000000000000000000000001100000000000000000000000000000000000000000000000000000000000000000000000000000000000000000000000000 !
b111000000000000000000000000000000000000000000000000000000000000000000000000000000000000000000000000000000000000000000000000000010110000000000000000000000000000000000000000000000000000000000000000000000000000000000000000000000000000000000000000000000000001011100000000000000000000000000000000000000000000000000000000000000000000000000000000000000000000000000000000000000000000000000001100000000000000000000000000000000000000000000000000000000000000000000000000000000000000000000000000 8
b1100 +
b1100 9"
b1010 J
b1010 5"
b1101 P
b1101 0"
b1101 2"
b1110 Q
b1110 +"
b1110 -"
b0 @
b0 '"
b0 8"
b0 R
b0 &"
b0 ("
b111 K
b111 !"
b1000 S
b1000 z
b1000 |
b0 T
b0 u
b0 w
b110 L
b110 k
b0 V
b0 f
b0 h
b0 7"
b0 "
b0 &
1$
#90000
0$
#95000
b0 L
b0 k
b0 S
b0 z
b0 |
b1000 K
b1000 !"
b0 Q
b0 +"
b0 -"
b1110 P
b1110 0"
b1110 2"
b1101 J
b1101 5"
b0 <
b0 ;"
b0 O
b0 :"
b0 <"
b1 N
b1 ?"
b1 A"
b1111 M
b1111 D"
b1111 F"
b1100 I
b1100 I"
1$
#100000
0$
#105000
b1111 I
b1111 I"
b1 M
b1 D"
b1 F"
b0 N
b0 ?"
b0 A"
b1110 J
b1110 5"
b0 P
b0 0"
b0 2"
b0 K
b0 !"
1$
#110000
0$
#115000
b0 J
b0 5"
b0 M
b0 D"
b0 F"
b1 I
b1 I"
1$
#120000
0$
#125000
b0 I
b0 I"
1$
