rtl/matmul_4x4/pe.v
module PE (
    input clk,
    input reset,
    input [7:0] in1,
    input [7:0] in2,
    output reg [7:0] out1,
    output reg [7:0] out2,
    output reg [31:0] mac_out
);

    always @(posedge clk or posedge reset) begin

        if(reset) begin
            mac_out <= 0;
            out1 <=  0;
            out2 <= 0;
        end
        else begin
            mac_out <= mac_out + (in1*in2);
            out1 <= in1;
            out2 <= in2;
        end

   end

endmodule

rtl/systolic_array.v
`include "pe.v"

module systolic_array (
    input clk,
    input reset,
    input [31:0] a,
    input [31:0] b,
    output [511:0] result
);

wire [7:0] a_in01, a_in02, a_in03, a_out1; 
wire [7:0] a_in11, a_in12, a_in13, a_out2; 
wire [7:0] a_in21, a_in22, a_in23, a_out3; 
wire [7:0] a_in31, a_in32, a_in33, a_out4;

wire [7:0] b_in10, b_in20, b_in30, b_out1;
wire [7:0] b_in11, b_in21, b_in31, b_out2;
wire [7:0] b_in12, b_in22, b_in32, b_out3;
wire [7:0] b_in13, b_in23, b_in33, b_out4;

wire [31:0] result_00, result_01, result_02, result_03;
wire [31:0] result_10, result_11, result_12, result_13;
wire [31:0] result_20, result_21, result_22, result_23;
wire [31:0] result_30, result_31, result_32, result_33;

PE pe_00 (clk, reset, a[7:0], b[7:0], a_in01, b_in10, result_00);
PE pe_01 (clk, reset, a_in01, b[15:8], a_in02, b_in11, result_01);
PE pe_02 (clk, reset, a_in02, b[23:16], a_in03, b_in12, result_02);
PE pe_03 (clk, reset, a_in03, b[31:24], a_out1, b_in13, result_03);

PE pe_10 (clk, reset, a[15:8], b_in10, a_in11, b_in20, result_10);
PE pe_11 (clk, reset, a_in11, b_in11, a_in12, b_in21, result_11);
PE pe_12 (clk, reset, a_in12, b_in12, a_in13, b_in22, result_12);
PE pe_13 (clk, reset, a_in13, b_in13, a_out2, b_in23, result_13);

PE pe_20 (clk, reset, a[23:16], b_in20, a_in21, b_in30, result_20);
PE pe_21 (clk, reset, a_in21, b_in21, a_in22, b_in31, result_21);
PE pe_22 (clk, reset, a_in22, b_in22, a_in23, b_in32, result_22);
PE pe_23 (clk, reset, a_in23, b_in23, a_out3, b_in33, result_23);

PE pe_30 (clk, reset, a[31:24], b_in30, a_in31, b_out1, result_30);
PE pe_31 (clk, reset, a_in31, b_in31, a_in32, b_out2, result_31);
PE pe_32 (clk, reset, a_in32, b_in32, a_in33, b_out3, result_32);
PE pe_33 (clk, reset, a_in33, b_in33, a_out4, b_out4, result_33);

assign result = { result_00, result_01, result_02, result_03,
                  result_10, result_11, result_12, result_13,
                  result_20, result_21, result_22, result_23,
                  result_30, result_31, result_32, result_33 };

endmodule

tb/systolic_array_matmul4x4_tb.v
`timescale 1ns/1ps

module matmul_tb;

    reg clk, reset;
    reg [31:0] a, b;
    wire [511:0] result;
    integer i;

    systolic_array uut(
        .clk(clk),
        .reset(reset),
        .a(a),
        .b(b),
        .result(result)
    );

    initial begin
        clk = 0;
        forever #5 clk = ~clk;
    end

    initial begin
        $dumpfile("matmul4x4_wave.vcd");
        $dumpvars(0, matmul_tb);
        
    end

    initial begin
        
        reset = 1;

        a = 32'h0;
        b = 32'h0;

        #10 reset = 0;

        @(posedge clk);

        a = 32'h00000001;
        b = 32'h00000001;

        @(posedge clk);

        a = 32'h00000502;
        b = 32'h00000502;

        @(posedge clk);

        a = 32'h00090603;
        b = 32'h00090603;

        @(posedge clk);

        a = 32'h0D0A0704;
        b = 32'h0D0A0704;

        @(posedge clk);

        a = 32'h0E0B0800;
        b = 32'h0E0B0800;

        @(posedge clk);

        a = 32'h0F0C0000;
        b = 32'h0F0C0000;

        @(posedge clk);

        a = 32'h01000000;
        b = 32'h01000000;

        @(posedge clk);

        a = 32'h0;
        b = 32'h0;

        repeat(10) @(posedge clk);

        // A:             B:
        // 1 2 3 4        1 5 9 13
        // 5 6 7 8        2 6 10 14
        // 9 10 11 12     3 7 11 15
        // 13 14 15 1     4 8 12 1

        // Result :
        // 30 70 110 90
        // 70 174 278 262
        // 110 278 446 434
        // 90 262 434 591

        $display("========================");
        $display("Result : ");

        for(i=0; i < 4; i = i + 1) begin
            $display("%0d %0d %0d %0d", result[(15 - i*4)*32 +: 32], result[(14 - i*4)*32 +: 32], result[(13 - i*4)*32 +: 32], result[(12 - i*4)*32 +: 32]);
        end
        $display("========================");

        #10

        $finish;

    end


endmodule

sim/matmul_4x4_sim/matmul4x4_wave.vcd
$date
	Thu Jan 15 15:57:11 2026
$end
$version
	Icarus Verilog
$end
$timescale
	1ps
$end
$scope module matmul_tb $end
$var wire 512 ! result [511:0] $end
$var reg 32 " a [31:0] $end
$var reg 32 # b [31:0] $end
$var reg 1 $ clk $end
$var reg 1 % reset $end
$var integer 32 & i [31:0] $end
$scope module uut $end
$var wire 32 ' a [31:0] $end
$var wire 32 ( b [31:0] $end
$var wire 1 $ clk $end
$var wire 1 % reset $end
$var wire 32 ) result_33 [31:0] $end
$var wire 32 * result_32 [31:0] $end
$var wire 32 + result_31 [31:0] $end
$var wire 32 , result_30 [31:0] $end
$var wire 32 - result_23 [31:0] $end
$var wire 32 . result_22 [31:0] $end
$var wire 32 / result_21 [31:0] $end
$var wire 32 0 result_20 [31:0] $end
$var wire 32 1 result_13 [31:0] $end
$var wire 32 2 result_12 [31:0] $end
$var wire 32 3 result_11 [31:0] $end
$var wire 32 4 result_10 [31:0] $end
$var wire 32 5 result_03 [31:0] $end
$var wire 32 6 result_02 [31:0] $end
$var wire 32 7 result_01 [31:0] $end
$var wire 32 8 result_00 [31:0] $end
$var wire 512 9 result [511:0] $end
$var wire 8 : b_out4 [7:0] $end
$var wire 8 ; b_out3 [7:0] $end
$var wire 8 < b_out2 [7:0] $end
$var wire 8 = b_out1 [7:0] $end
$var wire 8 > b_in33 [7:0] $end
$var wire 8 ? b_in32 [7:0] $end
$var wire 8 @ b_in31 [7:0] $end
$var wire 8 A b_in30 [7:0] $end
$var wire 8 B b_in23 [7:0] $end
$var wire 8 C b_in22 [7:0] $end
$var wire 8 D b_in21 [7:0] $end
$var wire 8 E b_in20 [7:0] $end
$var wire 8 F b_in13 [7:0] $end
$var wire 8 G b_in12 [7:0] $end
$var wire 8 H b_in11 [7:0] $end
$var wire 8 I b_in10 [7:0] $end
$var wire 8 J a_out4 [7:0] $end
$var wire 8 K a_out3 [7:0] $end
$var wire 8 L a_out2 [7:0] $end
$var wire 8 M a_out1 [7:0] $end
$var wire 8 N a_in33 [7:0] $end
$var wire 8 O a_in32 [7:0] $end
$var wire 8 P a_in31 [7:0] $end
$var wire 8 Q a_in23 [7:0] $end
$var wire 8 R a_in22 [7:0] $end
$var wire 8 S a_in21 [7:0] $end
$var wire 8 T a_in13 [7:0] $end
$var wire 8 U a_in12 [7:0] $end
$var wire 8 V a_in11 [7:0] $end
$var wire 8 W a_in03 [7:0] $end
$var wire 8 X a_in02 [7:0] $end
$var wire 8 Y a_in01 [7:0] $end
$scope module pe_00 $end
$var wire 1 $ clk $end
$var wire 8 Z in1 [7:0] $end
$var wire 8 [ in2 [7:0] $end
$var wire 1 % reset $end
$var reg 32 \ mac_out [31:0] $end
$var reg 8 ] out1 [7:0] $end
$var reg 8 ^ out2 [7:0] $end
$upscope $end
$scope module pe_01 $end
$var wire 1 $ clk $end
$var wire 8 _ in1 [7:0] $end
$var wire 8 ` in2 [7:0] $end
$var wire 1 % reset $end
$var reg 32 a mac_out [31:0] $end
$var reg 8 b out1 [7:0] $end
$var reg 8 c out2 [7:0] $end
$upscope $end
$scope module pe_02 $end
$var wire 1 $ clk $end
$var wire 8 d in1 [7:0] $end
$var wire 8 e in2 [7:0] $end
$var wire 1 % reset $end
$var reg 32 f mac_out [31:0] $end
$var reg 8 g out1 [7:0] $end
$var reg 8 h out2 [7:0] $end
$upscope $end
$scope module pe_03 $end
$var wire 1 $ clk $end
$var wire 8 i in1 [7:0] $end
$var wire 8 j in2 [7:0] $end
$var wire 1 % reset $end
$var reg 32 k mac_out [31:0] $end
$var reg 8 l out1 [7:0] $end
$var reg 8 m out2 [7:0] $end
$upscope $end
$scope module pe_10 $end
$var wire 1 $ clk $end
$var wire 8 n in1 [7:0] $end
$var wire 8 o in2 [7:0] $end
$var wire 1 % reset $end
$var reg 32 p mac_out [31:0] $end
$var reg 8 q out1 [7:0] $end
$var reg 8 r out2 [7:0] $end
$upscope $end
$scope module pe_11 $end
$var wire 1 $ clk $end
$var wire 8 s in1 [7:0] $end
$var wire 8 t in2 [7:0] $end
$var wire 1 % reset $end
$var reg 32 u mac_out [31:0] $end
$var reg 8 v out1 [7:0] $end
$var reg 8 w out2 [7:0] $end
$upscope $end
$scope module pe_12 $end
$var wire 1 $ clk $end
$var wire 8 x in1 [7:0] $end
$var wire 8 y in2 [7:0] $end
$var wire 1 % reset $end
$var reg 32 z mac_out [31:0] $end
$var reg 8 { out1 [7:0] $end
$var reg 8 | out2 [7:0] $end
$upscope $end
$scope module pe_13 $end
$var wire 1 $ clk $end
$var wire 8 } in1 [7:0] $end
$var wire 8 ~ in2 [7:0] $end
$var wire 1 % reset $end
$var reg 32 !" mac_out [31:0] $end
$var reg 8 "" out1 [7:0] $end
$var reg 8 #" out2 [7:0] $end
$upscope $end
$scope module pe_20 $end
$var wire 1 $ clk $end
$var wire 8 $" in1 [7:0] $end
$var wire 8 %" in2 [7:0] $end
$var wire 1 % reset $end
$var reg 32 &" mac_out [31:0] $end
$var reg 8 '" out1 [7:0] $end
$var reg 8 (" out2 [7:0] $end
$upscope $end
$scope module pe_21 $end
$var wire 1 $ clk $end
$var wire 8 )" in1 [7:0] $end
$var wire 8 *" in2 [7:0] $end
$var wire 1 % reset $end
$var reg 32 +" mac_out [31:0] $end
$var reg 8 ," out1 [7:0] $end
$var reg 8 -" out2 [7:0] $end
$upscope $end
$scope module pe_22 $end
$var wire 1 $ clk $end
$var wire 8 ." in1 [7:0] $end
$var wire 8 /" in2 [7:0] $end
$var wire 1 % reset $end
$var reg 32 0" mac_out [31:0] $end
$var reg 8 1" out1 [7:0] $end
$var reg 8 2" out2 [7:0] $end
$upscope $end
$scope module pe_23 $end
$var wire 1 $ clk $end
$var wire 8 3" in1 [7:0] $end
$var wire 8 4" in2 [7:0] $end
$var wire 1 % reset $end
$var reg 32 5" mac_out [31:0] $end
$var reg 8 6" out1 [7:0] $end
$var reg 8 7" out2 [7:0] $end
$upscope $end
$scope module pe_30 $end
$var wire 1 $ clk $end
$var wire 8 8" in1 [7:0] $end
$var wire 8 9" in2 [7:0] $end
$var wire 1 % reset $end
$var reg 32 :" mac_out [31:0] $end
$var reg 8 ;" out1 [7:0] $end
$var reg 8 <" out2 [7:0] $end
$upscope $end
$scope module pe_31 $end
$var wire 1 $ clk $end
$var wire 8 =" in1 [7:0] $end
$var wire 8 >" in2 [7:0] $end
$var wire 1 % reset $end
$var reg 32 ?" mac_out [31:0] $end
$var reg 8 @" out1 [7:0] $end
$var reg 8 A" out2 [7:0] $end
$upscope $end
$scope module pe_32 $end
$var wire 1 $ clk $end
$var wire 8 B" in1 [7:0] $end
$var wire 8 C" in2 [7:0] $end
$var wire 1 % reset $end
$var reg 32 D" mac_out [31:0] $end
$var reg 8 E" out1 [7:0] $end
$var reg 8 F" out2 [7:0] $end
$upscope $end
$scope module pe_33 $end
$var wire 1 $ clk $end
$var wire 8 G" in1 [7:0] $end
$var wire 8 H" in2 [7:0] $end
$var wire 1 % reset $end
$var reg 32 I" mac_out [31:0] $end
$var reg 8 J" out1 [7:0] $end
$var reg 8 K" out2 [7:0] $end
$upscope $end
$upscope $end
$upscope $end
$enddefinitions $end
#0
$dumpvars
b0 K"
b0 J"
b0 I"
b0 H"
b0 G"
b0 F"
b0 E"
b0 D"
b0 C"
b0 B"
b0 A"
b0 @"
b0 ?"
b0 >"
b0 ="
b0 <"
b0 ;"
b0 :"
b0 9"
b0 8"
b0 7"
b0 6"
b0 5"
b0 4"
b0 3"
b0 2"
b0 1"
b0 0"
b0 /"
b0 ."
b0 -"
b0 ,"
b0 +"
b0 *"
b0 )"
b0 ("
b0 '"
b0 &"
b0 %"
b0 $"
b0 #"
b0 ""
b0 !"
b0 ~
b0 }
b0 |
b0 {
b0 z
b0 y
b0 x
b0 w
b0 v
b0 u
b0 t
b0 s
b0 r
b0 q
b0 p
b0 o
b0 n
b0 m
b0 l
b0 k
b0 j
b0 i
b0 h
b0 g
b0 f
b0 e
b0 d
b0 c
b0 b
b0 a
b0 `
b0 _
b0 ^
b0 ]
b0 \
b0 [
b0 Z
b0 Y
b0 X
b0 W
b0 V
b0 U
b0 T
b0 S
b0 R
b0 Q
b0 P
b0 O
b0 N
b0 M
b0 L
b0 K
b0 J
b0 I
b0 H
b0 G
b0 F
b0 E
b0 D
b0 C
b0 B
b0 A
b0 @
b0 ?
b0 >
b0 =
b0 <
b0 ;
b0 :
b0 9
b0 8
b0 7
b0 6
b0 5
b0 4
b0 3
b0 2
b0 1
b0 0
b0 /
b0 .
b0 -
b0 ,
b0 +
b0 *
b0 )
b0 (
b0 '
bx &
1%
0$
b0 #
b0 "
b0 !
$end
#5000
1$
#10000
0$
0%
#15000
b1 [
b1 Z
b1 #
b1 (
b1 "
b1 '
1$
#20000
0$
#25000
b1 I
b1 ^
b1 o
b1 Y
b1 ]
b1 _
b1000000000000000000000000000000000000000000000000000000000000000000000000000000000000000000000000000000000000000000000000000000000000000000000000000000000000000000000000000000000000000000000000000000000000000000000000000000000000000000000000000000000000000000000000000000000000000000000000000000000000000000000000000000000000000000000000000000000000000000000000000000000000000000000000000000000000000000000000000000000000000000000000000000000000000000000000000000000000000000000000 !
b1000000000000000000000000000000000000000000000000000000000000000000000000000000000000000000000000000000000000000000000000000000000000000000000000000000000000000000000000000000000000000000000000000000000000000000000000000000000000000000000000000000000000000000000000000000000000000000000000000000000000000000000000000000000000000000000000000000000000000000000000000000000000000000000000000000000000000000000000000000000000000000000000000000000000000000000000000000000000000000000000 9
b1 8
b1 \
b10 [
b101 `
b10 Z
b101 n
b10100000010 #
b10100000010 (
b10100000010 "
b10100000010 '
1$
#30000
0$
#35000
b10 I
b10 ^
b10 o
b10 Y
b10 ]
b10 _
b101 8
b101 \
b101 H
b101 c
b101 t
b1 X
b1 b
b1 d
b101 7
b101 a
b1 E
b1 r
b1 %"
b101 V
b101 q
b101 s
b101000000000000000000000000000001010000000000000000000000000000000000000000000000000000000000000000000000000000000000000000000001010000000000000000000000000000000000000000000000000000000000000000000000000000000000000000000000000000000000000000000000000000000000000000000000000000000000000000000000000000000000000000000000000000000000000000000000000000000000000000000000000000000000000000000000000000000000000000000000000000000000000000000000000000000000000000000000000000000000000000 !
b101000000000000000000000000000001010000000000000000000000000000000000000000000000000000000000000000000000000000000000000000000001010000000000000000000000000000000000000000000000000000000000000000000000000000000000000000000000000000000000000000000000000000000000000000000000000000000000000000000000000000000000000000000000000000000000000000000000000000000000000000000000000000000000000000000000000000000000000000000000000000000000000000000000000000000000000000000000000000000000000000 9
b101 4
b101 p
b11 [
b110 `
b1001 e
b11 Z
b110 n
b1001 $"
b10010000011000000011 #
b10010000011000000011 (
b10010000011000000011 "
b10010000011000000011 '
1$
#40000
0$
#45000
b1 A
b1 ("
b1 9"
b1001 S
b1001 '"
b1001 )"
b1001 0
b1001 &"
b101 D
b101 w
b101 *"
b101 U
b101 v
b101 x
b11001 3
b11001 u
b10 E
b10 r
b10 %"
b110 V
b110 q
b110 s
b10001 4
b10001 p
b1001 G
b1001 h
b1001 y
b1 W
b1 g
b1 i
b1001 6
b1001 f
b110 H
b110 c
b110 t
b10 X
b10 b
b10 d
b10001 7
b10001 a
b11 I
b11 ^
b11 o
b11 Y
b11 ]
b11 _
b1110000000000000000000000000000100010000000000000000000000000000100100000000000000000000000000000000000000000000000000000000000100010000000000000000000000000001100100000000000000000000000000000000000000000000000000000000000000000000000000000000000000000000100100000000000000000000000000000000000000000000000000000000000000000000000000000000000000000000000000000000000000000000000000000000000000000000000000000000000000000000000000000000000000000000000000000000000000000000000000000000 !
b1110000000000000000000000000000100010000000000000000000000000000100100000000000000000000000000000000000000000000000000000000000100010000000000000000000000000001100100000000000000000000000000000000000000000000000000000000000000000000000000000000000000000000100100000000000000000000000000000000000000000000000000000000000000000000000000000000000000000000000000000000000000000000000000000000000000000000000000000000000000000000000000000000000000000000000000000000000000000000000000000000 9
b1110 8
b1110 \
b100 [
b111 `
b1010 e
b1101 j
b100 Z
b111 n
b1010 $"
b1101 8"
b1101000010100000011100000100 #
b1101000010100000011100000100 (
b1101000010100000011100000100 "
b1101000010100000011100000100 '
1$
#50000
0$
#55000
b100 I
b100 ^
b100 o
b100 Y
b100 ]
b100 _
b11110 8
b11110 \
b111 H
b111 c
b111 t
b11 X
b11 b
b11 d
b100110 7
b100110 a
b1010 G
b1010 h
b1010 y
b10 W
b10 g
b10 i
b11101 6
b11101 f
b1101 F
b1101 m
b1101 ~
b1 M
b1 l
b1101 5
b1101 k
b11 E
b11 r
b11 %"
b111 V
b111 q
b111 s
b100110 4
b100110 p
b110 D
b110 w
b110 *"
b110 U
b110 v
b110 x
b111101 3
b111101 u
b1001 C
b1001 |
b1001 /"
b101 T
b101 {
b101 }
b101101 2
b101101 z
b10 A
b10 ("
b10 9"
b1010 S
b1010 '"
b1010 )"
b11101 0
b11101 &"
b101 @
b101 -"
b101 >"
b1001 R
b1001 ,"
b1001 ."
b101101 /
b101101 +"
b1 =
b1 <"
b1101 P
b1101 ;"
b1101 ="
b11110000000000000000000000000001001100000000000000000000000000001110100000000000000000000000000001101000000000000000000000000001001100000000000000000000000000011110100000000000000000000000000101101000000000000000000000000000000000000000000000000000000000001110100000000000000000000000000101101000000000000000000000000000000000000000000000000000000000000000000000000000000000000000000001101000000000000000000000000000000000000000000000000000000000000000000000000000000000000000000000000 !
b11110000000000000000000000000001001100000000000000000000000000001110100000000000000000000000000001101000000000000000000000000001001100000000000000000000000000011110100000000000000000000000000101101000000000000000000000000000000000000000000000000000000000001110100000000000000000000000000101101000000000000000000000000000000000000000000000000000000000000000000000000000000000000000000001101000000000000000000000000000000000000000000000000000000000000000000000000000000000000000000000000 9
b1101 ,
b1101 :"
b0 [
b1000 `
b1011 e
b1110 j
b0 Z
b1000 n
b1011 $"
b1110 8"
b1110000010110000100000000000 #
b1110000010110000100000000000 (
b1110000010110000100000000000 "
b1110000010110000100000000000 '
1$
#60000
0$
#65000
b101 <
b101 A"
b1101 O
b1101 @"
b1101 B"
b1000001 +
b1000001 ?"
b10 =
b10 <"
b1110 P
b1110 ;"
b1110 ="
b101001 ,
b101001 :"
b1001 ?
b1001 2"
b1001 C"
b1001 Q
b1001 1"
b1001 3"
b1010001 .
b1010001 0"
b110 @
b110 -"
b110 >"
b1010 R
b1010 ,"
b1010 ."
b1101001 /
b1101001 +"
b11 A
b11 ("
b11 9"
b1011 S
b1011 '"
b1011 )"
b111110 0
b111110 &"
b1101 B
b1101 #"
b1101 4"
b101 L
b101 ""
b1000001 1
b1000001 !"
b1010 C
b1010 |
b1010 /"
b110 T
b110 {
b110 }
b1101001 2
b1101001 z
b111 D
b111 w
b111 *"
b111 U
b111 v
b111 x
b1101110 3
b1101110 u
b100 E
b100 r
b100 %"
b1000 V
b1000 q
b1000 s
b1000110 4
b1000110 p
b1110 F
b1110 m
b1110 ~
b10 M
b10 l
b101001 5
b101001 k
b1011 G
b1011 h
b1011 y
b11 W
b11 g
b11 i
b111110 6
b111110 f
b1000 H
b1000 c
b1000 t
b100 X
b100 b
b100 d
b11110000000000000000000000000010001100000000000000000000000000011111000000000000000000000000000101001000000000000000000000000010001100000000000000000000000000110111000000000000000000000000001101001000000000000000000000000010000010000000000000000000000000011111000000000000000000000000001101001000000000000000000000000010100010000000000000000000000000000000000000000000000000000000000101001000000000000000000000000010000010000000000000000000000000000000000000000000000000000000000000000 !
b11110000000000000000000000000010001100000000000000000000000000011111000000000000000000000000000101001000000000000000000000000010001100000000000000000000000000110111000000000000000000000000001101001000000000000000000000000010000010000000000000000000000000011111000000000000000000000000001101001000000000000000000000000010100010000000000000000000000000000000000000000000000000000000000101001000000000000000000000000010000010000000000000000000000000000000000000000000000000000000000000000 9
b1000110 7
b1000110 a
b0 I
b0 ^
b0 o
b0 Y
b0 ]
b0 _
b0 `
b1100 e
b1111 j
b0 n
b1100 $"
b1111 8"
b1111000011000000000000000000 #
b1111000011000000000000000000 (
b1111000011000000000000000000 "
b1111000011000000000000000000 '
1$
#70000
0$
#75000
b0 H
b0 c
b0 t
b0 X
b0 b
b0 d
b1100 G
b1100 h
b1100 y
b100 W
b100 g
b100 i
b1101110 6
b1101110 f
b1111 F
b1111 m
b1111 ~
b11 M
b11 l
b1010110 5
b1010110 k
b0 E
b0 r
b0 %"
b0 V
b0 q
b0 s
b1000 D
b1000 w
b1000 *"
b1000 U
b1000 v
b1000 x
b10101110 3
b10101110 u
b1011 C
b1011 |
b1011 /"
b111 T
b111 {
b111 }
b10110110 2
b10110110 z
b1110 B
b1110 #"
b1110 4"
b110 L
b110 ""
b10010101 1
b10010101 !"
b100 A
b100 ("
b100 9"
b1100 S
b1100 '"
b1100 )"
b1101110 0
b1101110 &"
b111 @
b111 -"
b111 >"
b1011 R
b1011 ,"
b1011 ."
b10110110 /
b10110110 +"
b1010 ?
b1010 2"
b1010 C"
b1010 Q
b1010 1"
b1010 3"
b10110101 .
b10110101 0"
b1101 >
b1101 7"
b1101 H"
b1001 K
b1001 6"
b1110101 -
b1110101 5"
b11 =
b11 <"
b1111 P
b1111 ;"
b1111 ="
b1010110 ,
b1010110 :"
b110 <
b110 A"
b1110 O
b1110 @"
b1110 B"
b10010101 +
b10010101 ?"
b1001 ;
b1001 F"
b1101 N
b1101 E"
b1101 G"
b11110000000000000000000000000010001100000000000000000000000000110111000000000000000000000000001010110000000000000000000000000010001100000000000000000000000001010111000000000000000000000000010110110000000000000000000000000100101010000000000000000000000000110111000000000000000000000000010110110000000000000000000000000101101010000000000000000000000000111010100000000000000000000000001010110000000000000000000000000100101010000000000000000000000000111010100000000000000000000000000000000 !
b11110000000000000000000000000010001100000000000000000000000000110111000000000000000000000000001010110000000000000000000000000010001100000000000000000000000001010111000000000000000000000000010110110000000000000000000000000100101010000000000000000000000000110111000000000000000000000000010110110000000000000000000000000101101010000000000000000000000000111010100000000000000000000000001010110000000000000000000000000100101010000000000000000000000000111010100000000000000000000000000000000 9
b1110101 *
b1110101 D"
b0 e
b1 j
b0 $"
b1 8"
b1000000000000000000000000 #
b1000000000000000000000000 (
b1000000000000000000000000 "
b1000000000000000000000000 '
1$
#80000
0$
#85000
b1101 :
b1101 K"
b1101 J
b1101 J"
b10101001 )
b10101001 I"
b1010 ;
b1010 F"
b1110 N
b1110 E"
b1110 G"
b100000001 *
b100000001 D"
b111 <
b111 A"
b1111 O
b1111 @"
b1111 B"
b11111110 +
b11111110 ?"
b100 =
b100 <"
b1 P
b1 ;"
b1 ="
b1011010 ,
b1011010 :"
b1110 >
b1110 7"
b1110 H"
b1010 K
b1010 6"
b100000001 -
b100000001 5"
b1011 ?
b1011 2"
b1011 C"
b1011 Q
b1011 1"
b1011 3"
b100101110 .
b100101110 0"
b1000 @
b1000 -"
b1000 >"
b1100 R
b1100 ,"
b1100 ."
b100010110 /
b100010110 +"
b0 A
b0 ("
b0 9"
b0 S
b0 '"
b0 )"
b1111 B
b1111 #"
b1111 4"
b111 L
b111 ""
b11111110 1
b11111110 !"
b1100 C
b1100 |
b1100 /"
b1000 T
b1000 {
b1000 }
b100010110 2
b100010110 z
b0 D
b0 w
b0 *"
b0 U
b0 v
b0 x
b1 F
b1 m
b1 ~
b100 M
b100 l
b11110000000000000000000000000010001100000000000000000000000000110111000000000000000000000000001011010000000000000000000000000010001100000000000000000000000001010111000000000000000000000000100010110000000000000000000000000111111100000000000000000000000000110111000000000000000000000000100010110000000000000000000000001001011100000000000000000000000010000000100000000000000000000000001011010000000000000000000000000111111100000000000000000000000010000000100000000000000000000000010101001 !
b11110000000000000000000000000010001100000000000000000000000000110111000000000000000000000000001011010000000000000000000000000010001100000000000000000000000001010111000000000000000000000000100010110000000000000000000000000111111100000000000000000000000000110111000000000000000000000000100010110000000000000000000000001001011100000000000000000000000010000000100000000000000000000000001011010000000000000000000000000111111100000000000000000000000010000000100000000000000000000000010101001 9
b1011010 5
b1011010 k
b0 G
b0 h
b0 y
b0 W
b0 g
b0 i
b0 j
b0 8"
b0 #
b0 (
b0 "
b0 '
1$
#90000
0$
#95000
b0 F
b0 m
b0 ~
b0 M
b0 l
b0 C
b0 |
b0 /"
b0 T
b0 {
b0 }
b1 B
b1 #"
b1 4"
b1000 L
b1000 ""
b100000110 1
b100000110 !"
b0 @
b0 -"
b0 >"
b0 R
b0 ,"
b0 ."
b1100 ?
b1100 2"
b1100 C"
b1100 Q
b1100 1"
b1100 3"
b110111110 .
b110111110 0"
b1111 >
b1111 7"
b1111 H"
b1011 K
b1011 6"
b110100110 -
b110100110 5"
b0 =
b0 <"
b0 P
b0 ;"
b0 ="
b1000 <
b1000 A"
b1 O
b1 @"
b1 B"
b100000110 +
b100000110 ?"
b1011 ;
b1011 F"
b1111 N
b1111 E"
b1111 G"
b110100110 *
b110100110 D"
b1110 :
b1110 K"
b1110 J
b1110 J"
b11110000000000000000000000000010001100000000000000000000000000110111000000000000000000000000001011010000000000000000000000000010001100000000000000000000000001010111000000000000000000000000100010110000000000000000000000001000001100000000000000000000000000110111000000000000000000000000100010110000000000000000000000001101111100000000000000000000000011010011000000000000000000000000001011010000000000000000000000001000001100000000000000000000000011010011000000000000000000000000101101101 !
b11110000000000000000000000000010001100000000000000000000000000110111000000000000000000000000001011010000000000000000000000000010001100000000000000000000000001010111000000000000000000000000100010110000000000000000000000001000001100000000000000000000000000110111000000000000000000000000100010110000000000000000000000001101111100000000000000000000000011010011000000000000000000000000001011010000000000000000000000001000001100000000000000000000000011010011000000000000000000000000101101101 9
b101101101 )
b101101101 I"
1$
#100000
0$
#105000
b1111 :
b1111 K"
b1111 J
b1111 J"
b1001001110 )
b1001001110 I"
b1100 ;
b1100 F"
b1 N
b1 E"
b1 G"
b110110010 *
b110110010 D"
b0 <
b0 A"
b0 O
b0 @"
b0 B"
b1 >
b1 7"
b1 H"
b1100 K
b1100 6"
b11110000000000000000000000000010001100000000000000000000000000110111000000000000000000000000001011010000000000000000000000000010001100000000000000000000000001010111000000000000000000000000100010110000000000000000000000001000001100000000000000000000000000110111000000000000000000000000100010110000000000000000000000001101111100000000000000000000000011011001000000000000000000000000001011010000000000000000000000001000001100000000000000000000000011011001000000000000000000000001001001110 !
b11110000000000000000000000000010001100000000000000000000000000110111000000000000000000000000001011010000000000000000000000000010001100000000000000000000000001010111000000000000000000000000100010110000000000000000000000001000001100000000000000000000000000110111000000000000000000000000100010110000000000000000000000001101111100000000000000000000000011011001000000000000000000000000001011010000000000000000000000001000001100000000000000000000000011011001000000000000000000000001001001110 9
b110110010 -
b110110010 5"
b0 ?
b0 2"
b0 C"
b0 Q
b0 1"
b0 3"
b0 B
b0 #"
b0 4"
b0 L
b0 ""
1$
#110000
0$
#115000
b0 >
b0 7"
b0 H"
b0 K
b0 6"
b0 ;
b0 F"
b0 N
b0 E"
b0 G"
b1 :
b1 K"
b1 J
b1 J"
b11110000000000000000000000000010001100000000000000000000000000110111000000000000000000000000001011010000000000000000000000000010001100000000000000000000000001010111000000000000000000000000100010110000000000000000000000001000001100000000000000000000000000110111000000000000000000000000100010110000000000000000000000001101111100000000000000000000000011011001000000000000000000000000001011010000000000000000000000001000001100000000000000000000000011011001000000000000000000000001001001111 !
b11110000000000000000000000000010001100000000000000000000000000110111000000000000000000000000001011010000000000000000000000000010001100000000000000000000000001010111000000000000000000000000100010110000000000000000000000001000001100000000000000000000000000110111000000000000000000000000100010110000000000000000000000001101111100000000000000000000000011011001000000000000000000000000001011010000000000000000000000001000001100000000000000000000000011011001000000000000000000000001001001111 9
b1001001111 )
b1001001111 I"
1$
#120000
0$
#125000
b0 :
b0 K"
b0 J
b0 J"
1$
#130000
0$
#135000
1$
#140000
0$
#145000
1$
#150000
0$
#155000
1$
#160000
0$
#165000
1$
#170000
0$
#175000
1$
#180000
0$
#185000
b100 &
1$
